README.md
pyproject.toml
setup.py
fileosninja/__init__.py
fileosninja/file_manager.py
fileosninja/utils.py
fileosninja.egg-info/PKG-INFO
fileosninja.egg-info/SOURCES.txt
fileosninja.egg-info/dependency_links.txt
fileosninja.egg-info/top_level.txt
tests/__init__.py
tests/test_file_manager.py