Metadata-Version: 2.1
Name: fileosninja
Version: 0.0.3
Summary: A versatile Python module for streamlined file I/O operations and essential OS-related tasks. Simplify your code with the power of fileosninja, providing a cohesive and efficient solution for reading and writing files, along with seamless integration of operating system functionalities. Empower your projects with the core capabilities of fileosninja, designed for simplicity and performance.
Home-page: UNKNOWN
Author: Parneet Sidhu
Author-email: parneetsingh022@gmail.com
License: The Unlicense
Project-URL: Documentation, https://parneetsingh022.github.io/fileosninja/
Project-URL: Source, https://github.com/parneetsingh022/fileosninja
Keywords: file IO,OS operations,Python module,file handling,operating system utilities
Platform: UNKNOWN
Classifier: Development Status :: 1 - Planning
Classifier: Intended Audience :: Developers
Classifier: Programming Language :: Python :: 3
Classifier: Operating System :: Unix
Classifier: Operating System :: MacOS :: MacOS X
Classifier: Operating System :: Microsoft :: Windows
